k2hr3_osnl/__init__.py
k2hr3_osnl/cfg.py
k2hr3_osnl/endpoint.py
k2hr3_osnl/exceptions.py
k2hr3_osnl/httpresponse.py
k2hr3_osnl/useragent.py
k2hr3_osnl-1.0.8.dist-info/licenses/AUTHORS.rst
k2hr3_osnl-1.0.8.dist-info/licenses/LICENSE
k2hr3_osnl-1.0.8.dist-info/METADATA
k2hr3_osnl-1.0.8.dist-info/WHEEL
k2hr3_osnl-1.0.8.dist-info/entry_points.txt
k2hr3_osnl-1.0.8.dist-info/top_level.txt
k2hr3_osnl-1.0.8.dist-info/RECORD
