Metadata-Version: 2.4
Name: k2hr3_osnl
Version: 1.0.8
Summary: An OpenStack notification listener for the K2HR3 role-based ACL system
Author-email: Hirotaka Wakabayashi <hiwakaba@lycorp.co.jp>, Takeshi Nakatani <ggtakec@gmail.com>
Maintainer-email: Hirotaka Wakabayashi <hiwakaba@lycorp.co.jp>, Takeshi Nakatani <ggtakec@gmail.com>
License: MIT License
Project-URL: Homepage, https://github.com/yahoojapan/k2hr3_osnl
Project-URL: Documentation, https://k2hr3-osnl.readthedocs.org
Project-URL: Repository, https://github.com/yahoojapan/k2hr3_osnl.git
Project-URL: Bug Tracker, https://github.com/yahoojapan/k2hr3_osnl/issues
Project-URL: Changelog, https://github.com/yahoojapan/k2hr3_osnl/blob/master/HISTORY.rst
Keywords: k2hr3,antpickax,OpenStack,iaas,k2hdkc_dbaas
Classifier: Development Status :: 4 - Beta
Classifier: Programming Language :: Python
Classifier: Environment :: Console
Classifier: Environment :: OpenStack
Classifier: Intended Audience :: Developers
Classifier: Intended Audience :: Information Technology
Classifier: License :: OSI Approved :: MIT License
Classifier: Programming Language :: Python :: 3
Classifier: Programming Language :: Python :: 3.9
Requires-Python: >=3.9
License-File: LICENSE
License-File: AUTHORS.rst
Requires-Dist: oslo.config>=5.2.0
Requires-Dist: oslo.messaging>=5.17.1
Dynamic: license-file
